{
  "type": "language",
  "name": "english",
  "version": "7.4.0",
  "revision": null,
  "path": "application\/languages\/en",
  "repository": null,
  "sku": null,
  "date": "Wed, 16 Jul 2025 13:19:55 +0000",
  "title": "English",
  "description": null,
  "thumb": null,
  "developer": null,
  "authors": [
    "SocialEngine Core"
  ],
  "meta": {
    "date": "Wed, 16 Jul 2025 13:19:55 +0000",
    "title": "English",
    "description": null,
    "developer": null,
    "authors": [
      "SocialEngine Core"
    ],
    "changeLog": null
  },
  "actions": [
    
  ],
  "callback": null,
  "dependencies": null,
  "tests": [
    
  ],
  "permissions": [
    
  ],
  "structure": {
    "application\/languages\/en": {
      "type": "directory",
      "path": "application\/languages\/en",
      "structure": [
        {
          "path": "user.csv",
          "dir": false,
          "file": true,
          "perms": "0644",
          "size": 92180,
          "sha1": "f04a36842a4d1bac9f4d2cb2f76c5f44c0992778"
        },
        {
          "path": "hello-world.csv",
          "dir": false,
          "file": true,
          "perms": "0755",
          "size": 829,
          "sha1": "69aa432f1f0564762b7185154dbe25d983e9b0df"
        },
        {
          "path": "authorization.csv",
          "dir": false,
          "file": true,
          "perms": "0755",
          "size": 5057,
          "sha1": "ce57317270a6c2f4634a5889b4c7aab02c81377a"
        },
        {
          "path": "manifest.php",
          "dir": false,
          "file": true,
          "perms": "0644",
          "size": 430,
          "sha1": "12ba5aef0e800f66e60ae68c4e8bf5127f5ad54b"
        },
        {
          "path": "invite.csv",
          "dir": false,
          "file": true,
          "perms": "0755",
          "size": 10732,
          "sha1": "3c3f0b290114b82438b4adbf8cc45c0656a462d9"
        },
        {
          "path": "fields.csv",
          "dir": false,
          "file": true,
          "perms": "0755",
          "size": 6754,
          "sha1": "53594989e516ff2d33c0d27505e63d67d1d100e7"
        },
        {
          "path": "activity.csv",
          "dir": false,
          "file": true,
          "perms": "0755",
          "size": 51015,
          "sha1": "11d5b245dcbc6f5b527b189d1588bf9107fc4a87"
        },
        {
          "path": "payment.csv",
          "dir": false,
          "file": true,
          "perms": "0644",
          "size": 56457,
          "sha1": "9b0b590ba039861adedb5a2d9b5e19c9c90b3f1f"
        },
        {
          "path": "mobi.csv",
          "dir": false,
          "file": true,
          "perms": "0755",
          "size": 52,
          "sha1": "651c126612f03850397c71285cbe1ca06b336f4e"
        },
        {
          "path": "messages.csv",
          "dir": false,
          "file": true,
          "perms": "0755",
          "size": 3603,
          "sha1": "938d9d65c2bd29e12ceb5cbac543d71ebd06975f"
        },
        {
          "path": "comment.csv",
          "dir": false,
          "file": true,
          "perms": "0644",
          "size": 3784,
          "sha1": "b8b89d5e2bd7e26bd29be48bfd5fc76d494e2903"
        },
        {
          "path": "storage.csv",
          "dir": false,
          "file": true,
          "perms": "0755",
          "size": 1367,
          "sha1": "9601ecc15033138c28bde5730796101ad53d587a"
        },
        {
          "path": "core.csv",
          "dir": false,
          "file": true,
          "perms": "0644",
          "size": 109869,
          "sha1": "e9714ffeee103053dfd660e61b4450dc3bc5c8f0"
        },
        {
          "path": "announcement.csv",
          "dir": false,
          "file": true,
          "perms": "0755",
          "size": 1866,
          "sha1": "1a701e6bee4b3bb106f28f78159b4cd23a814844"
        },
        {
          "path": "network.csv",
          "dir": false,
          "file": true,
          "perms": "0755",
          "size": 3125,
          "sha1": "8e9ad695552972fa4c3d02586c1649ea95e2f13d"
        },
        {
          "path": "harmony.csv",
          "dir": false,
          "file": true,
          "perms": "0644",
          "size": 14797,
          "sha1": "76796abf3690445d2c4114267c8ed97150245b8f"
        }
      ]
    }
  }
}